{
  "source_id": "gdelt",
  "status": "error",
  "sample_http": {
    "url": "https://api.gdeltproject.org/api/v2/doc/doc",
    "final_url": "https://api.gdeltproject.org/api/v2/doc/doc",
    "status_code": null,
    "content_type": null,
    "text_head": "",
    "error": "ConnectTimeout(MaxRetryError(\"HTTPSConnectionPool(host='api.gdeltproject.org', port=443): Max retries exceeded with url: /api/v2/doc/doc?query=earthquake&mode=timelinevol&format=json&startdatetime=20220101000000&enddatetime=20220107235959 (Caused by ConnectTimeoutError(<HTTPSConnection(host='api.gdeltproject.org', port=443) at 0x106257250>, 'Connection to api.gdeltproject.org timed out. (connect timeout=12)'))\"))"
  },
  "top_level_keys": [],
  "sample_row": null,
  "time_grain": "timeline bucket, usually daily",
  "geo_grain": "query/global"
}